{
  "call": {
    "called_at": 1777669590,
    "classification": "DEVELOPING",
    "closed_at": null,
    "confidence": 58,
    "current_liquidity_usd": 15325.75,
    "current_mcap_usd": 39965.0,
    "current_price_usd": 0.00003996,
    "entry_liquidity_usd": 11649.77,
    "entry_mcap_usd": 23093.0,
    "entry_pair_dex": "pumpswap",
    "entry_price_usd": 0.00002309,
    "entry_top_holder_pct": 20.6296109123526,
    "exit_note": null,
    "exit_price_usd": null,
    "expires_at": 1777928790,
    "id": 93,
    "mint": "58ASeZHtiocyBuYeCRPPcExbHEAPXWid49pxuUDpump",
    "note": "horizon=MOONSHOT",
    "outcome_type": "active",
    "pct_from_call": 73.06193157210912,
    "peak_at": 1777669607,
    "peak_pct": 3.9411000433087873,
    "source": "notifier",
    "status": "active",
    "symbol": "Fartbuckle",
    "thesis_url": null,
    "trough_at": 1777669590,
    "trough_pct": 0.9961022087483729
  },
  "captured_at": 1777669679,
  "last_snapshot_ts": 1777669628,
  "snapshots": [
    {
      "bundle_pct": 1.030137844994,
      "buys_h1": 122,
      "classification": "DEVELOPING",
      "confidence": 58,
      "distribution": 54,
      "forensics_computed_at": 1777669470,
      "holder_count": 20,
      "insider_pct": 0.0,
      "liquidity_usd": 11706.31,
      "mcap_usd": 23320.0,
      "momentum": 63,
      "pair_dex": "pumpswap",
      "price_change_h1": -99.99,
      "price_usd": 0.00002332,
      "sells_h1": 79,
      "smart_money_count": 0,
      "sniper_pct": 46.9475542028072,
      "spring": 58,
      "timestamp": 1777669590,
      "token_address": "58ASeZHtiocyBuYeCRPPcExbHEAPXWid49pxuUDpump",
      "top10_pct": 35.477572154617704,
      "top5_pct": 28.9482021800804,
      "top_holder_pct": 20.6296109123526,
      "tx_rate": 96.77419354838709,
      "velocity": 1.0,
      "volume_h1_usd": 6465.9
    },
    {
      "bundle_pct": 1.030137844994,
      "buys_h1": 146,
      "classification": "DEVELOPING",
      "confidence": 58,
      "distribution": 54,
      "forensics_computed_at": 1777669470,
      "holder_count": 20,
      "insider_pct": 0.0,
      "liquidity_usd": 11877.49,
      "mcap_usd": 24005.0,
      "momentum": 62,
      "pair_dex": "pumpswap",
      "price_change_h1": -99.99,
      "price_usd": 0.000024,
      "sells_h1": 110,
      "smart_money_count": 0,
      "sniper_pct": 46.9475542028072,
      "spring": 58,
      "timestamp": 1777669607,
      "token_address": "58ASeZHtiocyBuYeCRPPcExbHEAPXWid49pxuUDpump",
      "top10_pct": 35.477572154617704,
      "top5_pct": 28.9482021800804,
      "top_holder_pct": 20.6296109123526,
      "tx_rate": 96.77419354838709,
      "velocity": 1.0,
      "volume_h1_usd": 8626.99
    },
    {
      "bundle_pct": 1.030137844994,
      "buys_h1": 146,
      "classification": "DEVELOPING",
      "confidence": 58,
      "distribution": 54,
      "forensics_computed_at": 1777669470,
      "holder_count": 20,
      "insider_pct": 0.0,
      "liquidity_usd": 11877.49,
      "mcap_usd": 24005.0,
      "momentum": 62,
      "pair_dex": "pumpswap",
      "price_change_h1": -99.99,
      "price_usd": 0.000024,
      "sells_h1": 110,
      "smart_money_count": 0,
      "sniper_pct": 46.9475542028072,
      "spring": 58,
      "timestamp": 1777669628,
      "token_address": "58ASeZHtiocyBuYeCRPPcExbHEAPXWid49pxuUDpump",
      "top10_pct": 35.477572154617704,
      "top5_pct": 28.9482021800804,
      "top_holder_pct": 20.6296109123526,
      "tx_rate": 96.77419354838709,
      "velocity": 1.0,
      "volume_h1_usd": 8626.99
    }
  ]
}