{
  "events": [
    {
      "ts": 1777668733,
      "kind": "alert",
      "tag": "DEV SELLING",
      "summary": "DEV_SELLING Htd7…pump · deployer down 42.6% (194237363 → 111446353)",
      "mint": "Htd7MbDBVoQaQsLM4d9kmSeVuX5FDdBCrqxrXNLXpump",
      "signature": null
    },
    {
      "ts": 1777668716,
      "kind": "alert",
      "tag": "DEV SELLING",
      "summary": "DEV_SELLING Htd7…pump · deployer down 46.9% (194237363 → 103131183)",
      "mint": "Htd7MbDBVoQaQsLM4d9kmSeVuX5FDdBCrqxrXNLXpump",
      "signature": null
    },
    {
      "ts": 1777668684,
      "kind": "alert",
      "tag": "DEV SELLING",
      "summary": "DEV_SELLING Htd7…pump · deployer down 46.9% (194237363 → 103131183)",
      "mint": "Htd7MbDBVoQaQsLM4d9kmSeVuX5FDdBCrqxrXNLXpump",
      "signature": null
    },
    {
      "ts": 1777668428,
      "kind": "call",
      "tag": "CALL FIRED",
      "summary": "$vampcoin at $9k mcap — entry frozen",
      "mint": "Eb3KevajAAyfTdKqj8FKHz6tvnJaqE5UkGunXqKfvamp",
      "signature": null
    },
    {
      "ts": 1777668411,
      "kind": "call",
      "tag": "CALL FIRED",
      "summary": "$STARCAT at $52k mcap — entry frozen",
      "mint": "3uyg2CuY74R8FrBLfJMgCkpGm7qzaShmH5uZJoNJpump",
      "signature": null
    },
    {
      "ts": 1777667922,
      "kind": "call",
      "tag": "CALL FIRED",
      "summary": "$KATIA at $7k mcap — entry frozen",
      "mint": "72CystEt1nfumCWW22S5Q3RNkzBDSSsA2b7FE8aCpump",
      "signature": null
    },
    {
      "ts": 1777667897,
      "kind": "alert",
      "tag": "DEV SELLING",
      "summary": "DEV_SELLING 5qkq…pump · deployer down 100.0% (166097373 → 0)",
      "mint": "5qkq98FwnNVxaRAXRhnFGX7hfrfGy9juk9GtsuPcpump",
      "signature": null
    },
    {
      "ts": 1777660154,
      "kind": "call",
      "tag": "CALL FIRED",
      "summary": "$PET at $8k mcap — entry frozen",
      "mint": "4Uyj3QDSnMFscFo3qncEs4mvrn5iNJJs4DLDLgLDpump",
      "signature": null
    },
    {
      "ts": 1777659019,
      "kind": "call",
      "tag": "CALL FIRED",
      "summary": "$Pets at $11k mcap — entry frozen",
      "mint": "H2oBpD4bAmzsyN51mDgxoY9GYnG5soFT4ZnCzFvKpump",
      "signature": null
    },
    {
      "ts": 1777656074,
      "kind": "call",
      "tag": "CALL FIRED",
      "summary": "$S&L at $49k mcap — entry frozen",
      "mint": "D5HvqYiwmvt7b7hkWvCYBEGKcTK6y8T8wXoRDQJrYXLt",
      "signature": null
    },
    {
      "ts": 1777653167,
      "kind": "call",
      "tag": "CALL FIRED",
      "summary": "$Crayon at $5k mcap — entry frozen",
      "mint": "Er1pcbrV1omVTzVxAKSA4FsnuExne8CpB27hj7B1pump",
      "signature": null
    }
  ],
  "tokens": {
    "Htd7MbDBVoQaQsLM4d9kmSeVuX5FDdBCrqxrXNLXpump": {
      "symbol": "scribpoop",
      "name": "scribbli poop",
      "mcap_usd": 189186.0,
      "price_usd": 0.0001891,
      "price_change_1h": 443.0,
      "price_change_24h": null,
      "liquidity_usd": 36196.15
    },
    "Eb3KevajAAyfTdKqj8FKHz6tvnJaqE5UkGunXqKfvamp": {
      "symbol": "vampcoin",
      "name": "vampcoin",
      "mcap_usd": 14214.0,
      "price_usd": 0.00001421,
      "price_change_1h": -99.99,
      "price_change_24h": null,
      "liquidity_usd": 9255.12
    },
    "5qkq98FwnNVxaRAXRhnFGX7hfrfGy9juk9GtsuPcpump": {
      "symbol": "PETS",
      "name": "Codex Pets",
      "mcap_usd": 5573.0,
      "price_usd": 5.573e-6,
      "price_change_1h": -98.73,
      "price_change_24h": null,
      "liquidity_usd": 6162.2
    },
    "72CystEt1nfumCWW22S5Q3RNkzBDSSsA2b7FE8aCpump": {
      "symbol": "KATIA",
      "name": "KATIA MALNIKOVA",
      "mcap_usd": 4095.0,
      "price_usd": 4.094e-6,
      "price_change_1h": -100.0,
      "price_change_24h": null,
      "liquidity_usd": 4916.65
    },
    "H2oBpD4bAmzsyN51mDgxoY9GYnG5soFT4ZnCzFvKpump": {
      "symbol": "Pets",
      "name": "Codex Pets",
      "mcap_usd": 10572.0,
      "price_usd": 0.00001094,
      "price_change_1h": -20.27,
      "price_change_24h": null,
      "liquidity_usd": 8060.75
    },
    "3uyg2CuY74R8FrBLfJMgCkpGm7qzaShmH5uZJoNJpump": {
      "symbol": "STARCAT",
      "name": "STARCAT",
      "mcap_usd": 66202.0,
      "price_usd": 0.0000662,
      "price_change_1h": 94.62,
      "price_change_24h": null,
      "liquidity_usd": 19876.5
    },
    "D5HvqYiwmvt7b7hkWvCYBEGKcTK6y8T8wXoRDQJrYXLt": {
      "symbol": "S&L",
      "name": "Sandy & Luna",
      "mcap_usd": 22662.0,
      "price_usd": 0.00002266,
      "price_change_1h": -54.29,
      "price_change_24h": null,
      "liquidity_usd": 12293.72
    },
    "4Uyj3QDSnMFscFo3qncEs4mvrn5iNJJs4DLDLgLDpump": {
      "symbol": "PET",
      "name": "Petification",
      "mcap_usd": 14639.0,
      "price_usd": 0.0000148,
      "price_change_1h": 20.17,
      "price_change_24h": null,
      "liquidity_usd": 9379.71
    },
    "Er1pcbrV1omVTzVxAKSA4FsnuExne8CpB27hj7B1pump": {
      "symbol": "Crayon",
      "name": "Crayonification",
      "mcap_usd": 2696.0,
      "price_usd": 2.697e-6,
      "price_change_1h": -27.71,
      "price_change_24h": null,
      "liquidity_usd": 4008.05
    }
  }
}