{
  "events": [
    {
      "ts": 1777190741,
      "kind": "alert",
      "tag": "VELOCITY CRASH",
      "summary": "VELOCITY_CRASH 3hPj…pump · vel 1.33x→0.29x · tpm 15.4",
      "mint": "3hPjuKcU2Bs2hGnwrkNnYFnmkUbJNsaPpM6MzRH7pump",
      "signature": null
    },
    {
      "ts": 1777190676,
      "kind": "alert",
      "tag": "CONCENTRATING",
      "summary": "CONCENTRATING 3hPj…pump · top 0.00%→7.93% (+7.93%) · DEVELOPING",
      "mint": "3hPjuKcU2Bs2hGnwrkNnYFnmkUbJNsaPpM6MzRH7pump",
      "signature": null
    },
    {
      "ts": 1777190676,
      "kind": "alert",
      "tag": "CLASSIFICATION CHANGE",
      "summary": "CLASSIFICATION_CHANGE 3hPj…pump · SURGE→DEVELOPING · top +7.93%",
      "mint": "3hPjuKcU2Bs2hGnwrkNnYFnmkUbJNsaPpM6MzRH7pump",
      "signature": null
    },
    {
      "ts": 1777190634,
      "kind": "alert",
      "tag": "CLASSIFICATION CHANGE",
      "summary": "CLASSIFICATION_CHANGE 3hPj…pump · STAIRCASE→DEVELOPING · top +0.07%",
      "mint": "3hPjuKcU2Bs2hGnwrkNnYFnmkUbJNsaPpM6MzRH7pump",
      "signature": null
    },
    {
      "ts": 1777190535,
      "kind": "alert",
      "tag": "CLASSIFICATION CHANGE",
      "summary": "CLASSIFICATION_CHANGE 3hPj…pump · DEVELOPING→STAIRCASE · top -0.03%",
      "mint": "3hPjuKcU2Bs2hGnwrkNnYFnmkUbJNsaPpM6MzRH7pump",
      "signature": null
    },
    {
      "ts": 1777190517,
      "kind": "alert",
      "tag": "CLASSIFICATION CHANGE",
      "summary": "CLASSIFICATION_CHANGE 3hPj…pump · STAIRCASE→DEVELOPING · top +0.00%",
      "mint": "3hPjuKcU2Bs2hGnwrkNnYFnmkUbJNsaPpM6MzRH7pump",
      "signature": null
    },
    {
      "ts": 1777190488,
      "kind": "alert",
      "tag": "CLASSIFICATION CHANGE",
      "summary": "CLASSIFICATION_CHANGE 3hPj…pump · DEVELOPING→STAIRCASE · top -0.00%",
      "mint": "3hPjuKcU2Bs2hGnwrkNnYFnmkUbJNsaPpM6MzRH7pump",
      "signature": null
    },
    {
      "ts": 1777190470,
      "kind": "alert",
      "tag": "CLASSIFICATION CHANGE",
      "summary": "CLASSIFICATION_CHANGE 3hPj…pump · STAIRCASE→DEVELOPING · top +0.07%",
      "mint": "3hPjuKcU2Bs2hGnwrkNnYFnmkUbJNsaPpM6MzRH7pump",
      "signature": null
    },
    {
      "ts": 1777190417,
      "kind": "alert",
      "tag": "CLASSIFICATION CHANGE",
      "summary": "CLASSIFICATION_CHANGE 3hPj…pump · DEVELOPING→STAIRCASE · top -0.00%",
      "mint": "3hPjuKcU2Bs2hGnwrkNnYFnmkUbJNsaPpM6MzRH7pump",
      "signature": null
    },
    {
      "ts": 1777190394,
      "kind": "alert",
      "tag": "CLASSIFICATION CHANGE",
      "summary": "CLASSIFICATION_CHANGE 3hPj…pump · STAIRCASE→DEVELOPING · top +0.06%",
      "mint": "3hPjuKcU2Bs2hGnwrkNnYFnmkUbJNsaPpM6MzRH7pump",
      "signature": null
    },
    {
      "ts": 1777190352,
      "kind": "alert",
      "tag": "CLASSIFICATION CHANGE",
      "summary": "CLASSIFICATION_CHANGE 3hPj…pump · DEVELOPING→STAIRCASE · top +0.01%",
      "mint": "3hPjuKcU2Bs2hGnwrkNnYFnmkUbJNsaPpM6MzRH7pump",
      "signature": null
    },
    {
      "ts": 1777190329,
      "kind": "alert",
      "tag": "CLASSIFICATION CHANGE",
      "summary": "CLASSIFICATION_CHANGE 3hPj…pump · STAIRCASE→DEVELOPING · top -0.00%",
      "mint": "3hPjuKcU2Bs2hGnwrkNnYFnmkUbJNsaPpM6MzRH7pump",
      "signature": null
    },
    {
      "ts": 1777190296,
      "kind": "alert",
      "tag": "DEVELOPING",
      "summary": "DEVELOPING 3N7c…pump · mom 82 · top 41.14% · 20 holders",
      "mint": "3N7cta2ZHYaeA2Fgy6ZkrTp6dRXPcaLxeW67xf3upump",
      "signature": null
    },
    {
      "ts": 1777190293,
      "kind": "alert",
      "tag": "CLASSIFICATION CHANGE",
      "summary": "CLASSIFICATION_CHANGE 3hPj…pump · DEVELOPING→STAIRCASE · top -0.05%",
      "mint": "3hPjuKcU2Bs2hGnwrkNnYFnmkUbJNsaPpM6MzRH7pump",
      "signature": null
    },
    {
      "ts": 1777190275,
      "kind": "alert",
      "tag": "VELOCITY CRASH",
      "summary": "VELOCITY_CRASH 3hPj…pump · vel 4.00x→0.39x · tpm 9.8",
      "mint": "3hPjuKcU2Bs2hGnwrkNnYFnmkUbJNsaPpM6MzRH7pump",
      "signature": null
    },
    {
      "ts": 1777190275,
      "kind": "alert",
      "tag": "CLASSIFICATION CHANGE",
      "summary": "CLASSIFICATION_CHANGE 3hPj…pump · STAIRCASE→DEVELOPING · top +0.17%",
      "mint": "3hPjuKcU2Bs2hGnwrkNnYFnmkUbJNsaPpM6MzRH7pump",
      "signature": null
    },
    {
      "ts": 1777190111,
      "kind": "alert",
      "tag": "CLASSIFICATION CHANGE",
      "summary": "CLASSIFICATION_CHANGE 3hPj…pump · DEVELOPING→STAIRCASE · top -0.01%",
      "mint": "3hPjuKcU2Bs2hGnwrkNnYFnmkUbJNsaPpM6MzRH7pump",
      "signature": null
    },
    {
      "ts": 1777190093,
      "kind": "alert",
      "tag": "CLASSIFICATION CHANGE",
      "summary": "CLASSIFICATION_CHANGE 3hPj…pump · STAIRCASE→DEVELOPING · top +0.14%",
      "mint": "3hPjuKcU2Bs2hGnwrkNnYFnmkUbJNsaPpM6MzRH7pump",
      "signature": null
    },
    {
      "ts": 1777190065,
      "kind": "alert",
      "tag": "CLASSIFICATION CHANGE",
      "summary": "CLASSIFICATION_CHANGE 3hPj…pump · DEVELOPING→STAIRCASE · top -0.01%",
      "mint": "3hPjuKcU2Bs2hGnwrkNnYFnmkUbJNsaPpM6MzRH7pump",
      "signature": null
    },
    {
      "ts": 1777190047,
      "kind": "alert",
      "tag": "CLASSIFICATION CHANGE",
      "summary": "CLASSIFICATION_CHANGE 3hPj…pump · STAIRCASE→DEVELOPING · top +0.00%",
      "mint": "3hPjuKcU2Bs2hGnwrkNnYFnmkUbJNsaPpM6MzRH7pump",
      "signature": null
    },
    {
      "ts": 1777189967,
      "kind": "alert",
      "tag": "CLASSIFICATION CHANGE",
      "summary": "CLASSIFICATION_CHANGE 3hPj…pump · DEVELOPING→STAIRCASE · top +0.00%",
      "mint": "3hPjuKcU2Bs2hGnwrkNnYFnmkUbJNsaPpM6MzRH7pump",
      "signature": null
    },
    {
      "ts": 1777189933,
      "kind": "alert",
      "tag": "CLASSIFICATION CHANGE",
      "summary": "CLASSIFICATION_CHANGE 3hPj…pump · STAIRCASE→DEVELOPING · top -0.01%",
      "mint": "3hPjuKcU2Bs2hGnwrkNnYFnmkUbJNsaPpM6MzRH7pump",
      "signature": null
    },
    {
      "ts": 1777189882,
      "kind": "alert",
      "tag": "CLASSIFICATION CHANGE",
      "summary": "CLASSIFICATION_CHANGE 3hPj…pump · DEVELOPING→STAIRCASE · top -0.01%",
      "mint": "3hPjuKcU2Bs2hGnwrkNnYFnmkUbJNsaPpM6MzRH7pump",
      "signature": null
    },
    {
      "ts": 1777189864,
      "kind": "alert",
      "tag": "CLASSIFICATION CHANGE",
      "summary": "CLASSIFICATION_CHANGE 3hPj…pump · STAIRCASE→DEVELOPING · top -0.12%",
      "mint": "3hPjuKcU2Bs2hGnwrkNnYFnmkUbJNsaPpM6MzRH7pump",
      "signature": null
    },
    {
      "ts": 1777189754,
      "kind": "alert",
      "tag": "CLASSIFICATION CHANGE",
      "summary": "CLASSIFICATION_CHANGE 3hPj…pump · DEVELOPING→STAIRCASE · top -0.18%",
      "mint": "3hPjuKcU2Bs2hGnwrkNnYFnmkUbJNsaPpM6MzRH7pump",
      "signature": null
    },
    {
      "ts": 1777189729,
      "kind": "alert",
      "tag": "CLASSIFICATION CHANGE",
      "summary": "CLASSIFICATION_CHANGE 3hPj…pump · STAIRCASE→DEVELOPING · top +0.00%",
      "mint": "3hPjuKcU2Bs2hGnwrkNnYFnmkUbJNsaPpM6MzRH7pump",
      "signature": null
    },
    {
      "ts": 1777189706,
      "kind": "alert",
      "tag": "CLASSIFICATION CHANGE",
      "summary": "CLASSIFICATION_CHANGE 3hPj…pump · DEVELOPING→STAIRCASE · top +0.01%",
      "mint": "3hPjuKcU2Bs2hGnwrkNnYFnmkUbJNsaPpM6MzRH7pump",
      "signature": null
    },
    {
      "ts": 1777189667,
      "kind": "alert",
      "tag": "CONCENTRATING",
      "summary": "CONCENTRATING 3hPj…pump · top 0.00%→7.96% (+7.96%) · DEVELOPING",
      "mint": "3hPjuKcU2Bs2hGnwrkNnYFnmkUbJNsaPpM6MzRH7pump",
      "signature": null
    },
    {
      "ts": 1777189667,
      "kind": "alert",
      "tag": "CLASSIFICATION CHANGE",
      "summary": "CLASSIFICATION_CHANGE 3hPj…pump · SURGE→DEVELOPING · top +7.96%",
      "mint": "3hPjuKcU2Bs2hGnwrkNnYFnmkUbJNsaPpM6MzRH7pump",
      "signature": null
    },
    {
      "ts": 1777189627,
      "kind": "alert",
      "tag": "CLASSIFICATION CHANGE",
      "summary": "CLASSIFICATION_CHANGE 3hPj…pump · STAIRCASE→DEVELOPING · top +0.01%",
      "mint": "3hPjuKcU2Bs2hGnwrkNnYFnmkUbJNsaPpM6MzRH7pump",
      "signature": null
    },
    {
      "ts": 1777189609,
      "kind": "alert",
      "tag": "CLASSIFICATION CHANGE",
      "summary": "CLASSIFICATION_CHANGE 3hPj…pump · DEVELOPING→STAIRCASE · top +0.16%",
      "mint": "3hPjuKcU2Bs2hGnwrkNnYFnmkUbJNsaPpM6MzRH7pump",
      "signature": null
    },
    {
      "ts": 1777189565,
      "kind": "alert",
      "tag": "VELOCITY CRASH",
      "summary": "VELOCITY_CRASH 3hPj…pump · vel 1.35x→0.31x · tpm 13.6",
      "mint": "3hPjuKcU2Bs2hGnwrkNnYFnmkUbJNsaPpM6MzRH7pump",
      "signature": null
    },
    {
      "ts": 1777189548,
      "kind": "alert",
      "tag": "CLASSIFICATION CHANGE",
      "summary": "CLASSIFICATION_CHANGE 3hPj…pump · STAIRCASE→DEVELOPING · top +0.04%",
      "mint": "3hPjuKcU2Bs2hGnwrkNnYFnmkUbJNsaPpM6MzRH7pump",
      "signature": null
    },
    {
      "ts": 1777189489,
      "kind": "alert",
      "tag": "CLASSIFICATION CHANGE",
      "summary": "CLASSIFICATION_CHANGE 3hPj…pump · DEVELOPING→STAIRCASE · top -0.03%",
      "mint": "3hPjuKcU2Bs2hGnwrkNnYFnmkUbJNsaPpM6MzRH7pump",
      "signature": null
    },
    {
      "ts": 1777189467,
      "kind": "alert",
      "tag": "VELOCITY CRASH",
      "summary": "VELOCITY_CRASH 3hPj…pump · vel 1.20x→0.28x · tpm 17.8",
      "mint": "3hPjuKcU2Bs2hGnwrkNnYFnmkUbJNsaPpM6MzRH7pump",
      "signature": null
    },
    {
      "ts": 1777189358,
      "kind": "alert",
      "tag": "VELOCITY CRASH",
      "summary": "VELOCITY_CRASH 3hPj…pump · vel 1.50x→0.46x · tpm 14.1",
      "mint": "3hPjuKcU2Bs2hGnwrkNnYFnmkUbJNsaPpM6MzRH7pump",
      "signature": null
    },
    {
      "ts": 1777189358,
      "kind": "alert",
      "tag": "CLASSIFICATION CHANGE",
      "summary": "CLASSIFICATION_CHANGE 3hPj…pump · STAIRCASE→DEVELOPING · top -0.03%",
      "mint": "3hPjuKcU2Bs2hGnwrkNnYFnmkUbJNsaPpM6MzRH7pump",
      "signature": null
    },
    {
      "ts": 1777189255,
      "kind": "alert",
      "tag": "CLASSIFICATION CHANGE",
      "summary": "CLASSIFICATION_CHANGE 3hPj…pump · DEVELOPING→STAIRCASE · top -0.03%",
      "mint": "3hPjuKcU2Bs2hGnwrkNnYFnmkUbJNsaPpM6MzRH7pump",
      "signature": null
    },
    {
      "ts": 1777189218,
      "kind": "alert",
      "tag": "CLASSIFICATION CHANGE",
      "summary": "CLASSIFICATION_CHANGE 3hPj…pump · STAIRCASE→DEVELOPING · top +0.01%",
      "mint": "3hPjuKcU2Bs2hGnwrkNnYFnmkUbJNsaPpM6MzRH7pump",
      "signature": null
    },
    {
      "ts": 1777187712,
      "kind": "call",
      "tag": "CALL FIRED",
      "summary": "$BLIMP at $82k mcap — entry frozen",
      "mint": "F4LYw83S51J4Dz9uZzeeGD1BbfYHJnEhF44dqyXepump",
      "signature": null
    },
    {
      "ts": 1777187607,
      "kind": "call",
      "tag": "CALL FIRED",
      "summary": "$EITHER at $12701k mcap — entry frozen",
      "mint": "HmBdm8vbisABUjkxms6ZUnoaXbfwFM6ymxShWfAENaoi",
      "signature": null
    },
    {
      "ts": 1777187589,
      "kind": "call",
      "tag": "CALL FIRED",
      "summary": "$Archangel at $174k mcap — entry frozen",
      "mint": "FqSxniFXc3AeRAkcs3vvZ62xfKJNcgswDtNnKC3Vpump",
      "signature": null
    },
    {
      "ts": 1777187490,
      "kind": "call",
      "tag": "CALL FIRED",
      "summary": "$MEOWJESTY at $169k mcap — entry frozen",
      "mint": "79YC3BkcgHKVg7imkadkVFu2kDRK3V6RUQ2iLFogpump",
      "signature": null
    },
    {
      "ts": 1777187390,
      "kind": "call",
      "tag": "CALL FIRED",
      "summary": "$Dunald at $351k mcap — entry frozen",
      "mint": "3hPjuKcU2Bs2hGnwrkNnYFnmkUbJNsaPpM6MzRH7pump",
      "signature": null
    },
    {
      "ts": 1777186941,
      "kind": "call",
      "tag": "CALL FIRED",
      "summary": "$SPIKE at $15825k mcap — entry frozen",
      "mint": "BFiGUxnidogqcZAPVPDZRCfhx3nXnFLYqpQUaUGpump",
      "signature": null
    },
    {
      "ts": 1777186726,
      "kind": "call",
      "tag": "CALL FIRED",
      "summary": "$abcdefg at $614k mcap — entry frozen",
      "mint": "89S7oVB4hui8ceJqhHreWB7fcxdthfvoB7z2pfJtpump",
      "signature": null
    },
    {
      "ts": 1777186356,
      "kind": "call",
      "tag": "CALL FIRED",
      "summary": "$HENRY at $990k mcap — entry frozen",
      "mint": "CJUrENDAuSm4FxxziUgftnUJqqXjm4VL1zhJgwXupump",
      "signature": null
    },
    {
      "ts": 1777186250,
      "kind": "call",
      "tag": "CALL FIRED",
      "summary": "$CATCOIN at $815k mcap — entry frozen",
      "mint": "5gTPspC2ricuGWiYQ4Ghausg8fsq7uCrGgSVACatcoin",
      "signature": null
    },
    {
      "ts": 1777186249,
      "kind": "call",
      "tag": "CALL FIRED",
      "summary": "$assface at $707k mcap — entry frozen",
      "mint": "BnXWvsVZYgBxTUDyDqHZjvFbQGvEZeipY4ZdmqCbpump",
      "signature": null
    },
    {
      "ts": 1777186055,
      "kind": "call",
      "tag": "CALL FIRED",
      "summary": "$Kiss at $90k mcap — entry frozen",
      "mint": "7KunmzqV5sbK8awVSjNjC3TGS9QPwbgCyrPynZBYpump",
      "signature": null
    }
  ]
}